aio_geojson_flightairmap/__init__.py
aio_geojson_flightairmap/__version__.py
aio_geojson_flightairmap/consts.py
aio_geojson_flightairmap/feed.py
aio_geojson_flightairmap/feed_entry.py
aio_geojson_flightairmap/feed_manager.py
aio_geojson_flightairmap-0.4.21.dist-info/LICENSE
aio_geojson_flightairmap-0.4.21.dist-info/METADATA
aio_geojson_flightairmap-0.4.21.dist-info/WHEEL
aio_geojson_flightairmap-0.4.21.dist-info/top_level.txt
aio_geojson_flightairmap-0.4.21.dist-info/RECORD
