Metadata-Version: 2.1
Name: aio-geojson-flightairmap
Version: 0.4.21
Summary: An async GeoJSON client library for planes using information from a Flight Air Map server.
Home-page: https://github.com/kuchel77/python-aio-geojson-flightairmap
Author: Mark Kuchel
Author-email: mark@kuchel.net
License: UNKNOWN
Platform: UNKNOWN
Classifier: Programming Language :: Python :: 3.6
Classifier: Programming Language :: Python :: 3.7
Classifier: Programming Language :: Python :: 3.8
Classifier: License :: OSI Approved :: Apache Software License
Classifier: Operating System :: OS Independent
Requires-Dist: aio-geojson-client (>=0.11)
Requires-Dist: aiohttp (>=3.5.4)
Requires-Dist: pytz (>=2019.01)
